FfmpegJiaocheng/README.md
FfmpegJiaocheng/__init__.py
FfmpegJiaocheng/__main__.py
FfmpegJiaocheng/file.epub
FfmpegJiaocheng/index.html
FfmpegJiaocheng/css/__init__.py
FfmpegJiaocheng/css/annotations.css
FfmpegJiaocheng/css/main.css
FfmpegJiaocheng/css/normalize.css
FfmpegJiaocheng/css/popup.css
FfmpegJiaocheng/font/__init__.py
FfmpegJiaocheng/font/fontello.eot
FfmpegJiaocheng/font/fontello.svg
FfmpegJiaocheng/font/fontello.ttf
FfmpegJiaocheng/font/fontello.woff
FfmpegJiaocheng/img/__init__.py
FfmpegJiaocheng/img/annotator-glyph-sprite.png
FfmpegJiaocheng/img/annotator-icon-sprite.png
FfmpegJiaocheng/img/apple-touch-icon.png
FfmpegJiaocheng/img/cancelfullscreen.png
FfmpegJiaocheng/img/close.png
FfmpegJiaocheng/img/fullscreen.png
FfmpegJiaocheng/img/loader.gif
FfmpegJiaocheng/img/menu-icon.png
FfmpegJiaocheng/img/save.png
FfmpegJiaocheng/img/saved.png
FfmpegJiaocheng/img/settings-s.png
FfmpegJiaocheng/img/settings.png
FfmpegJiaocheng/img/star.png
FfmpegJiaocheng/js/__init__.py
FfmpegJiaocheng/js/epub.js
FfmpegJiaocheng/js/epub.min.js
FfmpegJiaocheng/js/epub.min.map
FfmpegJiaocheng/js/hooks.min.js
FfmpegJiaocheng/js/hooks.min.map
FfmpegJiaocheng/js/reader.js
FfmpegJiaocheng/js/reader.js.map
FfmpegJiaocheng/js/reader.min.js
FfmpegJiaocheng/js/reader.min.map
FfmpegJiaocheng/js/hooks/__init__.py
FfmpegJiaocheng/js/hooks/extensions/__init__.py
FfmpegJiaocheng/js/hooks/extensions/highlight.js
FfmpegJiaocheng/js/libs/__init__.py
FfmpegJiaocheng/js/libs/jquery.min.js
FfmpegJiaocheng/js/libs/localforage.min.js
FfmpegJiaocheng/js/libs/screenfull.js
FfmpegJiaocheng/js/libs/screenfull.min.js
FfmpegJiaocheng/js/libs/zip.min.js
FfmpegJiaocheng/js/plugins/__init__.py
FfmpegJiaocheng/js/plugins/hypothesis.js
FfmpegJiaocheng/js/plugins/search.js
ffmpeg_jiaocheng-2024.3.5.0.dist-info/METADATA
ffmpeg_jiaocheng-2024.3.5.0.dist-info/WHEEL
ffmpeg_jiaocheng-2024.3.5.0.dist-info/entry_points.txt
ffmpeg_jiaocheng-2024.3.5.0.dist-info/top_level.txt
ffmpeg_jiaocheng-2024.3.5.0.dist-info/RECORD
